villa_x/__init__.py
villa_x/villa_x.py
villa_x-0.0.5.dist-info/METADATA
villa_x-0.0.5.dist-info/WHEEL
villa_x-0.0.5.dist-info/licenses/LICENSE
villa_x-0.0.5.dist-info/RECORD
