Metadata-Version: 2.4
Name: ViLLa-X
Version: 0.0.5
Summary: ViLLa-X
Project-URL: Homepage, https://pypi.org/project/villa-x/
Project-URL: Repository, https://github.com/lucidrains/villa-x
Author-email: Phil Wang <lucidrains@gmail.com>
License: MIT License
License-File: LICENSE
Keywords: artificial intelligence,attention mechanism,deep learning,flow policy,latent actions,robotics,transformers
Classifier: Development Status :: 4 - Beta
Classifier: Intended Audience :: Developers
Classifier: License :: OSI Approved :: MIT License
Classifier: Programming Language :: Python :: 3.9
Classifier: Topic :: Scientific/Engineering :: Artificial Intelligence
Requires-Python: >=3.9
Requires-Dist: axial-positional-embedding>=0.3.12
Requires-Dist: einops>=0.8.1
Requires-Dist: einx>=0.3.0
Requires-Dist: rectified-flow-pytorch>=0.4.5
Requires-Dist: torch>=2.4
Requires-Dist: torchvision
Requires-Dist: transformers
Requires-Dist: vector-quantize-pytorch>=1.22.18
Requires-Dist: vit-pytorch
Requires-Dist: x-mlps-pytorch
Requires-Dist: x-transformers>=2.6.7
Provides-Extra: examples
Provides-Extra: test
Requires-Dist: pytest; extra == 'test'
